py_pesapal/__init__.py
py_pesapal/pesapal.py
py_pesapal/pesapal_flask.py
py_pesapal/utils.py
py_pesapal-0.1.0.dist-info/LICENCE
py_pesapal-0.1.0.dist-info/METADATA
py_pesapal-0.1.0.dist-info/WHEEL
py_pesapal-0.1.0.dist-info/top_level.txt
py_pesapal-0.1.0.dist-info/RECORD
