Metadata-Version: 2.1
Name: py-pesapal
Version: 0.1.0
Summary: PesaPal integration made easy
Home-page: https://github.com/M69k65y/py-pesapal
Author: M69k65y
License: MIT
Keywords: pesapal flask python
Platform: UNKNOWN
Classifier: Development Status :: 5 - Production/Stable
Classifier: Framework :: Flask
Classifier: Intended Audience :: Developers
Classifier: License :: OSI Approved :: MIT License
Classifier: Natural Language :: English
Classifier: Programming Language :: Python :: 3
Requires-Dist: requests (>=2.22.0requests_oauthlib>=1.3.0)
